traktor_server/__init__.py
traktor_server/__main__.py
traktor_server/asgi.py
traktor_server/config.py
traktor_server/errors.py
traktor_server/exception_handler.py
traktor_server/log.py
traktor_server/settings.py
traktor_server/urls.py
traktor_server/version.py
traktor_server/wsgi.py
traktor_server/commands/__init__.py
traktor_server/commands/app.py
traktor_server/migrations/__init__.py
traktor_server/models/__init__.py
traktor_server/serializers/__init__.py
traktor_server/serializers/serializers.py
traktor_server/serializers/validators.py
traktor_server/views/__init__.py
traktor_server/views/api/__init__.py
traktor_server/views/api/v0/__init__.py
traktor_server/views/api/v0/api.py
traktor_server/views/api/v0/auth.py
traktor_server/views/api/v0/urls.py
traktor_server-0.0.3.dist-info/AUTHORS
traktor_server-0.0.3.dist-info/LICENSE
traktor_server-0.0.3.dist-info/METADATA
traktor_server-0.0.3.dist-info/WHEEL
traktor_server-0.0.3.dist-info/entry_points.txt
traktor_server-0.0.3.dist-info/top_level.txt
traktor_server-0.0.3.dist-info/RECORD
