Metadata-Version: 2.1
Name: traktor-server
Version: 0.0.3
Summary: Sever for traktor app.
Home-page: https://github.com/alefnula/traktor-server
Author: Viktor Kerkez
Author-email: alefnula@gmail.com
Maintainer: Viktor Kerkez
Maintainer-email: alefnula@gmail.com
License: Apache-2.0
Platform: Windows
Platform: POSIX
Platform: MacOSX
Classifier: Programming Language :: Python :: 3
Classifier: Programming Language :: Python :: 3.7
Classifier: Programming Language :: Python :: 3.8
Classifier: License :: OSI Approved :: Apache Software License
Classifier: Operating System :: OS Independent
Requires-Dist: django (==3.1)
Requires-Dist: djangorestframework (==3.11.1)
Requires-Dist: djangorestframework-jwt (==1.11.0)
Requires-Dist: gunicorn (==20.0.4)
Requires-Dist: tea-console (==0.0.3)
Requires-Dist: tea-django (==0.0.5)
Requires-Dist: traktor (==0.0.4)
